nemglo/__init__.py
nemglo/api.py
nemglo/backend/input_validation.py
nemglo/backend/optimiser_formatters.py
nemglo/backend/solver_operator.py
nemglo/components/electrolyser.py
nemglo/components/emissions.py
nemglo/components/renewables.py
nemglo/defaults.py
nemglo/defaults_plot.py
nemglo/lite.py
nemglo/planning/data_fetch.py
nemglo/planning/planner.py
nemglo-0.3.0.dist-info/LICENSE
nemglo-0.3.0.dist-info/WHEEL
nemglo-0.3.0.dist-info/METADATA
nemglo-0.3.0.dist-info/RECORD
