Metadata-Version: 2.1
Name: nemglo
Version: 0.3.0
Summary: Green-energy Load Optimisation tool for the NEM
License: BSD-3-Clause license
Author: dec-heim
Author-email: 92137442+dec-heim@users.noreply.github.com
Requires-Python: >=3.9,<4.0
Classifier: License :: Other/Proprietary License
Classifier: Programming Language :: Python :: 3
Classifier: Programming Language :: Python :: 3.9
Classifier: Programming Language :: Python :: 3.10
Requires-Dist: flask (>=2.2.2,<3.0.0)
Requires-Dist: flask-cors (>=3.0.10,<4.0.0)
Requires-Dist: mip (>=1.13.0,<2.0.0)
Requires-Dist: nemed
Requires-Dist: nemosis (>=3.1.0,<4.0.0)
Requires-Dist: numpy (>=1.23.1,<2.0.0)
Requires-Dist: pandas (>=1.4.3,<2.0.0)
Requires-Dist: pyyaml (>=6.0,<7.0)
